gcloud/__init__.py
gcloud/_helpers.py
gcloud/_testing.py
gcloud/client.py
gcloud/connection.py
gcloud/credentials.py
gcloud/environment_vars.py
gcloud/exceptions.py
gcloud/iterator.py
gcloud/test__helpers.py
gcloud/test_client.py
gcloud/test_connection.py
gcloud/test_credentials.py
gcloud/test_exceptions.py
gcloud/test_iterator.py
gcloud/bigquery/__init__.py
gcloud/bigquery/_helpers.py
gcloud/bigquery/client.py
gcloud/bigquery/connection.py
gcloud/bigquery/dataset.py
gcloud/bigquery/job.py
gcloud/bigquery/query.py
gcloud/bigquery/table.py
gcloud/bigquery/test__helpers.py
gcloud/bigquery/test_client.py
gcloud/bigquery/test_connection.py
gcloud/bigquery/test_dataset.py
gcloud/bigquery/test_job.py
gcloud/bigquery/test_query.py
gcloud/bigquery/test_table.py
gcloud/bigtable/__init__.py
gcloud/bigtable/_testing.py
gcloud/bigtable/client.py
gcloud/bigtable/cluster.py
gcloud/bigtable/column_family.py
gcloud/bigtable/row.py
gcloud/bigtable/row_data.py
gcloud/bigtable/row_filters.py
gcloud/bigtable/table.py
gcloud/bigtable/test_client.py
gcloud/bigtable/test_cluster.py
gcloud/bigtable/test_column_family.py
gcloud/bigtable/test_row.py
gcloud/bigtable/test_row_data.py
gcloud/bigtable/test_row_filters.py
gcloud/bigtable/test_table.py
gcloud/bigtable/_generated/__init__.py
gcloud/bigtable/_generated/bigtable_cluster_data_pb2.py
gcloud/bigtable/_generated/bigtable_cluster_service_messages_pb2.py
gcloud/bigtable/_generated/bigtable_cluster_service_pb2.py
gcloud/bigtable/_generated/bigtable_data_pb2.py
gcloud/bigtable/_generated/bigtable_service_messages_pb2.py
gcloud/bigtable/_generated/bigtable_service_pb2.py
gcloud/bigtable/_generated/bigtable_table_data_pb2.py
gcloud/bigtable/_generated/bigtable_table_service_messages_pb2.py
gcloud/bigtable/_generated/bigtable_table_service_pb2.py
gcloud/bigtable/_generated/operations_grpc_pb2.py
gcloud/bigtable/_generated/_bigtable_cluster_data.proto
gcloud-0.15.0.dist-info/top_level.txt
gcloud-0.15.0.dist-info/METADATA
gcloud-0.15.0.dist-info/DESCRIPTION.rst
gcloud-0.15.0.dist-info/metadata.json
gcloud-0.15.0.dist-info/WHEEL
gcloud-0.15.0.dist-info/RECORD
