Metadata-Version: 1.1
Name: gcloud
Version: 0.15.0
Summary: API Client library for Google Cloud
Home-page: https://github.com/GoogleCloudPlatform/gcloud-python
Author: Google Cloud Platform
Author-email: jjg+gcloud-python@google.com
License: Apache 2.0
Platform: Posix; MacOS X; Windows
Classifier: Development Status :: 4 - Beta
Classifier: Intended Audience :: Developers
Classifier: License :: OSI Approved :: Apache Software License
Classifier: Operating System :: OS Independent
Classifier: Programming Language :: Python :: 2
Classifier: Programming Language :: Python :: 2.6
Classifier: Programming Language :: Python :: 2.7
Classifier: Programming Language :: Python :: 3
Classifier: Programming Language :: Python :: 3.4
Classifier: Programming Language :: Python :: 3.5
Classifier: Topic :: Internet
